{
    "Яндекс":
    {
        "start_url": "https://events.yandex.ru/",
        "event_url":
        {
            "page": "start",
            "selectors":
            {
                "event-card__title": ["a", "class", "href"]
            }
        },
        "reg_url":
        {
            "page": "event",
            "selectors":
            {
            	"events-info__registration-button": ["a", "class", "href"]
            }
        },
        "title":
        {
            "page": "start",
            "selectors":
            {
                "event-card__title": ["a", "class", "title"]
            }
        },
        "date":
        {
            "page": "event",
            "selectors":
            {
                "event-card__date": ["div", "class", "text"]
            }
        },
        "time":
        {
            "page": "event",
            "selectors":
            {
            	"events-program-item__time" : ["div", "class", "text"],
            	"events-info__registration-date" : ["div", "class", "text"],
            	"EventHeader__address" : ["div", "class", "text"]
            }
        },
        "location":
        {
            "page": "event",
            "selectors":
            {
            	"events-info__location" : ["div", "class", "text"]
            }
        },
        "price":
        {
            "page": "event",
            "default": "0",
            "selectors":
            {

            }
        },
        "language":
        {
            "page": "event",
            "default": "ru",
            "selectors":
            {

            }

        },
        "themes":
        {
        	"page": "event",
        	"selectors":
        	{
        		"events-program-item__talk" : ["div", "class", "text"]
        	}
        },
        "speakers":
        {
            "page": "event",
            "selectors":
            {
            	"speaker__name" : ["div", "class", "text"]
            }
        },
        "speakers_companies":
        {
            "page": "event",
            "selectors":
            {
            	"speaker__company" : ["div", "class", "text"]
            }
        },
        "online_status": {
        	"page": "event",
        	"selectors":
        	{
        		"EventHeader__place": ["span", "class", "text"],
        		"events-info__with-translation" : ["div", "class", "text"],
        		"events-info__online" : ["div", "class", "text"]
        	}
        },
        "organizers":
        {
            "page": "event",
            "default": "Яндекс",
            "selectors":
            {

            }
        },
        "prize":
        {
            "page": "event",
            "selectors":
            {

            }
        },
        "tags":
        {
            "page": "event",
            "selectors":
            {

            }
        },
        "type":
        {
            "page": "event",
            "selectors":
            {

            }
        }
    },
    "Data Fest": {
        "name": "Data Fest",
        "url": "https://fest.ai/"
    },
    "ods.ai Competitions":{
        "name": "ods.ai Competitions",
        "url": "https://ods.ai/competitions",
        "type": "competition"
    },
    "Russian Hackers":
    {
        "name": "Russian Hackers",
        "url": "https://russianhackers.org/"
    },
    "Авито":
    {
        "name": "События Avito",
        "url": "https://tech.avito.ru/events/"
    },
    "Тинькофф":
    {
        "name": "Митапы Тинькофф",
        "url": "https://meetup.tinkoff.ru/upcoming/"
    },
    "EPAM":
    {
        "name": "EPAM",
        "url": "https://events.epam.com/"
    },
    "IT-Events":
    {
        "name": "IT-Events",
        "url": "https://it-events.com/"
    },
    "dev.by":
    {
        "name": "ИТ в Беларуси",
        "url": "https://events.dev.by/"
    },
    "DOU":
    {
        "name": "Сообщество программистов Украины",
        "url": "https://dou.ua/calendar/"
    },
    "ITVDN":
    {
        "name": "ITVDN",
        "url": "https://itvdn.com/ru/webinars"
    },
    "IAMPM":
    {
        "name": "IAMPM",
        "url": "https://events.iampm.club/",
        "func": "iampm"
    },
    "ЦФТ":
    {
        "name": "Центр Финансовых Технологий",
        "url": "https://team.cft.ru/events/",
        "func": "cft"
    }
}